{
  "version": "7",
  "dialect": "postgresql",
  "entries": [
    {
      "idx": 0,
      "version": "7",
      "when": 1764338558057,
      "tag": "0000_robust_menace",
      "breakpoints": true
    },
    {
      "idx": 1,
      "version": "7",
      "when": 1764417309253,
      "tag": "0001_productive_fenris",
      "breakpoints": true
    },
    {
      "idx": 2,
      "version": "7",
      "when": 1764420620881,
      "tag": "0002_big_the_fury",
      "breakpoints": true
    },
    {
      "idx": 3,
      "version": "7",
      "when": 1764428184811,
      "tag": "0003_modern_spitfire",
      "breakpoints": true
    },
    {
      "idx": 4,
      "version": "7",
      "when": 1764502121477,
      "tag": "0004_grey_anita_blake",
      "breakpoints": true
    }
  ]
}